pathlib_requests/__init__.py
pathlib_requests/main.py
pathlib_requests/main_slower.py
pathlib_requests_nemkov-0.1.1.dist-info/METADATA
pathlib_requests_nemkov-0.1.1.dist-info/WHEEL
pathlib_requests_nemkov-0.1.1.dist-info/RECORD
