Metadata-Version: 2.3
Name: pathlib-requests-nemkov
Version: 0.1.1
Summary: 
Author: roBoot-LDT
Author-email: maksim.nemkov.ldt@gmail.com
Requires-Python: >=3.13
Classifier: Programming Language :: Python :: 3
Classifier: Programming Language :: Python :: 3.13
Requires-Dist: aiofiles (==24.1.0)
Requires-Dist: aiohappyeyeballs (==2.6.1)
Requires-Dist: aiohttp (==3.11.18)
Requires-Dist: aiohttp (>=3.11.18,<4.0.0)
Requires-Dist: aiosignal (==1.3.2)
Requires-Dist: attrs (==25.3.0)
Requires-Dist: certifi (==2025.4.26)
Requires-Dist: charset-normalizer (==3.4.2)
Requires-Dist: dotenv (==0.9.9)
Requires-Dist: frozenlist (==1.6.0)
Requires-Dist: idna (==3.10)
Requires-Dist: multidict (==6.4.3)
Requires-Dist: propcache (==0.3.1)
Requires-Dist: python-dotenv (==1.1.0)
Requires-Dist: requests (==2.32.3)
Requires-Dist: urllib3 (==2.4.0)
Requires-Dist: yarl (==1.20.0)
